LICENSE.txt
MANIFEST.in
README.rst
setup.cfg
setup.py
chinesepostman/__init__.py
chinesepostman/dijkstra.py
chinesepostman/eularian.py
chinesepostman/my_iter.py
chinesepostman/my_math.py
chinesepostman/network.py
chinesepostman.egg-info/PKG-INFO
chinesepostman.egg-info/SOURCES.txt
chinesepostman.egg-info/dependency_links.txt
chinesepostman.egg-info/top_level.txt
data/__init__.py
data/__init__.pyc
data/data.py
data/data.pyc
data/north.png
data/pacific-spirit.png
data/pacific-spirit_map.png
data/south.png
data/__pycache__/__init__.cpython-34.pyc
data/__pycache__/__init__.cpython-35.pyc
data/__pycache__/data.cpython-34.pyc
data/__pycache__/data.cpython-35.pyc