Metadata-Version: 1.1
Name: chinesepostman
Version: 0.0.2
Summary: Chinese-Postman network solver
Home-page: https://github.com/supermitch/Chinese-Postman
Author: Mitch LeBlanc
Author-email: supermitch@gmail.com
License: MIT
Keywords: graph network solver postman chinese
Platform: UNKNOWN
Classifier: Development Status :: 3 - Alpha
Classifier: Environment :: Console
Classifier: Intended Audience :: Developers
Classifier: License :: OSI Approved :: MIT License
Classifier: Natural Language :: English
Classifier: Operating System :: OS Independent
Classifier: Programming Language :: Python
Classifier: Topic :: Utilities
